MANIFEST.in
README.md
setup.py
perin_parser/__init__.py
perin_parser/dataset.py
perin_parser/params.py
perin_parser/perin_parser.py
perin_parser/preprocess.py
perin_parser/train.py
perin_parser.egg-info/PKG-INFO
perin_parser.egg-info/SOURCES.txt
perin_parser.egg-info/dependency_links.txt
perin_parser.egg-info/requires.txt
perin_parser.egg-info/top_level.txt
perin_parser/data/__init__.py
perin_parser/data/batch.py
perin_parser/data/concat_dataset.py
perin_parser/data/dataset.py
perin_parser/data/shared_dataset.py
perin_parser/data/field/__init__.py
perin_parser/data/field/anchor_field.py
perin_parser/data/field/basic_field.py
perin_parser/data/field/bert_field.py
perin_parser/data/field/edge_field.py
perin_parser/data/field/edge_label_field.py
perin_parser/data/field/edge_permutation_field.py
perin_parser/data/field/field.py
perin_parser/data/field/nested_field.py
perin_parser/data/field/property_field.py
perin_parser/data/field/relative_label_field.py
perin_parser/data/parser/__init__.py
perin_parser/data/parser/json_parser.py
perin_parser/data/parser/from_mrp/__init__.py
perin_parser/data/parser/from_mrp/abstract_parser.py
perin_parser/data/parser/from_mrp/amr_parser.py
perin_parser/data/parser/from_mrp/drg_parser.py
perin_parser/data/parser/from_mrp/eds_parser.py
perin_parser/data/parser/from_mrp/evaluation_parser.py
perin_parser/data/parser/from_mrp/ptg_parser.py
perin_parser/data/parser/from_mrp/request_parser.py
perin_parser/data/parser/from_mrp/ucca_parser.py
perin_parser/data/parser/to_mrp/__init__.py
perin_parser/data/parser/to_mrp/abstract_parser.py
perin_parser/data/parser/to_mrp/amr_parser.py
perin_parser/data/parser/to_mrp/drg_parser.py
perin_parser/data/parser/to_mrp/eds_parser.py
perin_parser/data/parser/to_mrp/ptg_parser.py
perin_parser/data/parser/to_mrp/ucca_parser.py
perin_parser/model/__init__.py
perin_parser/model/model.py
perin_parser/model/head/__init__.py
perin_parser/model/head/abstract_head.py
perin_parser/model/head/amr_head.py
perin_parser/model/head/drg_head.py
perin_parser/model/head/eds_head.py
perin_parser/model/head/ptg_head.py
perin_parser/model/head/ucca_head.py
perin_parser/model/module/__init__.py
