Metadata-Version: 2.1
Name: perin-parser
Version: 0.0.17
Summary: (Unofficial) PERIN: Permutation-invariant Semantic Parsing
Home-page: https://github.com/ufal/perin
Author: David Samuel & Milan Straka
License: Mozilla Public License 2.0
Keywords: corpus,machine-learning,NLU,NLP
Platform: UNKNOWN
Classifier: Intended Audience :: Science/Research
Classifier: Intended Audience :: Developers
Classifier: Development Status :: 3 - Alpha
Classifier: Operating System :: OS Independent
Classifier: License :: OSI Approved :: Apache Software License
Classifier: Programming Language :: Python :: 3 :: Only
Classifier: Topic :: Scientific/Engineering :: Artificial Intelligence
Classifier: Topic :: Text Processing :: Linguistic
Requires-Python: >=3.6
